{
  "dist/cli.js": {
    "path": "dist/cli.js",
    "content": "#!/usr/bin/env node\n\"use strict\";\nvar __importDefault = (this && this.__importDefault) || function (mod) {\n    return (mod && mod.__esModule) ? mod : { \"default\": mod };\n};\nObject.defineProperty(exports, \"__esModule\", { value: true });\nconst fileCollector_1 = require(\"./fileCollector\");\nconst path_1 = __importDefault(require(\"path\"));\nconst yargs_1 = __importDefault(require(\"yargs\"));\nconst helpers_1 = require(\"yargs/helpers\");\n(async () => {\n    const rootDir = process.cwd();\n    const argv = await (0, yargs_1.default)((0, helpers_1.hideBin)(process.argv))\n        .option('includeDirs', {\n        type: 'array',\n        description: 'Directories to include',\n    })\n        .option('excludeDirs', {\n        type: 'array',\n        default: ['node_modules'],\n        description: 'Directories to exclude',\n    })\n        .option('outputFormat', {\n        type: 'string',\n        choices: ['txt', 'json'],\n        default: 'json',\n        description: 'Output file format',\n    })\n        .option('outputPath', {\n        type: 'string',\n        default: 'output.txt',\n        description: 'Path to save the output file',\n    })\n        .demandCommand(0)\n        .help()\n        .argv;\n    console.log(argv);\n    const collector = new fileCollector_1.FileCollector(rootDir, {\n        includeDirs: argv.includeDirs,\n        excludeDirs: argv.excludeDirs,\n        outputFormat: argv.outputFormat,\n    });\n    await collector.saveOutput(path_1.default.resolve(argv.outputPath));\n})();\n"
  },
  "dist/fileCollector.js": {
    "path": "dist/fileCollector.js",
    "content": "\"use strict\";\nvar __importDefault = (this && this.__importDefault) || function (mod) {\n    return (mod && mod.__esModule) ? mod : { \"default\": mod };\n};\nObject.defineProperty(exports, \"__esModule\", { value: true });\nexports.FileCollector = void 0;\nconst fs_1 = __importDefault(require(\"fs\"));\nconst path_1 = __importDefault(require(\"path\"));\nclass FileCollector {\n    constructor(rootDir, options = {}) {\n        this.rootDir = rootDir;\n        this.includeDirs = options.includeDirs || [];\n        this.excludeDirs = options.excludeDirs || ['node_modules'];\n        this.outputFormat = options.outputFormat || 'json';\n    }\n    async collectFiles(dir) {\n        const files = [];\n        const entries = await fs_1.default.promises.readdir(dir, { withFileTypes: true });\n        for (const entry of entries) {\n            const fullPath = path_1.default.join(dir, entry.name);\n            if (entry.isDirectory()) {\n                const relativePath = path_1.default.relative(this.rootDir, fullPath);\n                if (!this.excludeDirs.includes(relativePath)) {\n                    files.push(...(await this.collectFiles(fullPath)));\n                }\n            }\n            else {\n                files.push(fullPath);\n            }\n        }\n        return files;\n    }\n    async generateTxt(files) {\n        return files\n            .map((file) => {\n            const content = fs_1.default.readFileSync(file, 'utf-8');\n            const relativePath = path_1.default.relative(this.rootDir, file);\n            return `__FILE_PATH__\\n${relativePath}\\n__FILE_CONTENT__\\n${content}\\n__END_OF_FILE__`;\n        })\n            .join('\\n');\n    }\n    async generateJson(files) {\n        const output = {};\n        for (const file of files) {\n            const content = fs_1.default.readFileSync(file, 'utf-8');\n            const relativePath = path_1.default.relative(this.rootDir, file);\n            output[relativePath] = { path: relativePath, content };\n        }\n        return output;\n    }\n    async generateOutput() {\n        const files = await this.collectFiles(this.rootDir);\n        if (this.outputFormat === 'txt') {\n            return this.generateTxt(files);\n        }\n        else {\n            return this.generateJson(files);\n        }\n    }\n    async saveOutput(outputPath) {\n        const output = await this.generateOutput();\n        if (this.outputFormat === 'txt') {\n            fs_1.default.writeFileSync(outputPath, output, 'utf-8');\n        }\n        else {\n            fs_1.default.writeFileSync(outputPath, JSON.stringify(output, null, 2), 'utf-8');\n        }\n    }\n}\nexports.FileCollector = FileCollector;\n"
  },
  "dist/index.js": {
    "path": "dist/index.js",
    "content": "\"use strict\";\nObject.defineProperty(exports, \"__esModule\", { value: true });\nexports.FileCollector = void 0;\nvar fileCollector_1 = require(\"./fileCollector\");\nObject.defineProperty(exports, \"FileCollector\", { enumerable: true, get: function () { return fileCollector_1.FileCollector; } });\n"
  },
  "output.json": {
    "path": "output.json",
    "content": "{\n  \"package-lock.json\": {\n    \"path\": \"package-lock.json\",\n    \"content\": \"{\\n  \\\"name\\\": \\\"source-collector\\\",\\n  \\\"version\\\": \\\"0.0.1\\\",\\n  \\\"lockfileVersion\\\": 3,\\n  \\\"requires\\\": true,\\n  \\\"packages\\\": {\\n    \\\"\\\": {\\n      \\\"name\\\": \\\"source-collector\\\",\\n      \\\"version\\\": \\\"0.0.1\\\",\\n      \\\"license\\\": \\\"MIT\\\",\\n      \\\"dependencies\\\": {\\n        \\\"yargs\\\": \\\"^17.7.2\\\"\\n      },\\n      \\\"bin\\\": {\\n        \\\"file-collector\\\": \\\"dist/cli.js\\\"\\n      },\\n      \\\"devDependencies\\\": {\\n        \\\"@types/node\\\": \\\"^22.10.10\\\",\\n        \\\"@types/yargs\\\": \\\"^17.0.33\\\",\\n        \\\"typescript\\\": \\\"^5.2.0\\\"\\n      }\\n    },\\n    \\\"node_modules/@types/node\\\": {\\n      \\\"version\\\": \\\"22.10.10\\\",\\n      \\\"resolved\\\": \\\"https://registry.npmjs.org/@types/node/-/node-22.10.10.tgz\\\",\\n      \\\"integrity\\\": \\\"sha512-X47y/mPNzxviAGY5TcYPtYL8JsY3kAq2n8fMmKoRCxq/c4v4pyGNCzM2R6+M5/umG4ZfHuT+sgqDYqWc9rJ6ww==\\\",\\n      \\\"dev\\\": true,\\n      \\\"license\\\": \\\"MIT\\\",\\n      \\\"dependencies\\\": {\\n        \\\"undici-types\\\": \\\"~6.20.0\\\"\\n      }\\n    },\\n    \\\"node_modules/@types/yargs\\\": {\\n      \\\"version\\\": \\\"17.0.33\\\",\\n      \\\"resolved\\\": \\\"https://registry.npmjs.org/@types/yargs/-/yargs-17.0.33.tgz\\\",\\n      \\\"integrity\\\": \\\"sha512-WpxBCKWPLr4xSsHgz511rFJAM+wS28w2zEO1QDNY5zM/S8ok70NNfztH0xwhqKyaK0OHCbN98LDAZuy1ctxDkA==\\\",\\n      \\\"dev\\\": true,\\n      \\\"license\\\": \\\"MIT\\\",\\n      \\\"dependencies\\\": {\\n        \\\"@types/yargs-parser\\\": \\\"*\\\"\\n      }\\n    },\\n    \\\"node_modules/@types/yargs-parser\\\": {\\n      \\\"version\\\": \\\"21.0.3\\\",\\n      \\\"resolved\\\": \\\"https://registry.npmjs.org/@types/yargs-parser/-/yargs-parser-21.0.3.tgz\\\",\\n      \\\"integrity\\\": \\\"sha512-I4q9QU9MQv4oEOz4tAHJtNz1cwuLxn2F3xcc2iV5WdqLPpUnj30aUuxt1mAxYTG+oe8CZMV/+6rU4S4gRDzqtQ==\\\",\\n      \\\"dev\\\": true,\\n      \\\"license\\\": \\\"MIT\\\"\\n    },\\n    \\\"node_modules/ansi-regex\\\": {\\n      \\\"version\\\": \\\"5.0.1\\\",\\n      \\\"resolved\\\": \\\"https://registry.npmjs.org/ansi-regex/-/ansi-regex-5.0.1.tgz\\\",\\n      \\\"integrity\\\": \\\"sha512-quJQXlTSUGL2LH9SUXo8VwsY4soanhgo6LNSm84E1LBcE8s3O0wpdiRzyR9z/ZZJMlMWv37qOOb9pdJlMUEKFQ==\\\",\\n      \\\"license\\\": \\\"MIT\\\",\\n      \\\"engines\\\": {\\n        \\\"node\\\": \\\">=8\\\"\\n      }\\n    },\\n    \\\"node_modules/ansi-styles\\\": {\\n      \\\"version\\\": \\\"4.3.0\\\",\\n      \\\"resolved\\\": \\\"https://registry.npmjs.org/ansi-styles/-/ansi-styles-4.3.0.tgz\\\",\\n      \\\"integrity\\\": \\\"sha512-zbB9rCJAT1rbjiVDb2hqKFHNYLxgtk8NURxZ3IZwD3F6NtxbXZQCnnSi1Lkx+IDohdPlFp222wVALIheZJQSEg==\\\",\\n      \\\"license\\\": \\\"MIT\\\",\\n      \\\"dependencies\\\": {\\n        \\\"color-convert\\\": \\\"^2.0.1\\\"\\n      },\\n      \\\"engines\\\": {\\n        \\\"node\\\": \\\">=8\\\"\\n      },\\n      \\\"funding\\\": {\\n        \\\"url\\\": \\\"https://github.com/chalk/ansi-styles?sponsor=1\\\"\\n      }\\n    },\\n    \\\"node_modules/cliui\\\": {\\n      \\\"version\\\": \\\"8.0.1\\\",\\n      \\\"resolved\\\": \\\"https://registry.npmjs.org/cliui/-/cliui-8.0.1.tgz\\\",\\n      \\\"integrity\\\": \\\"sha512-BSeNnyus75C4//NQ9gQt1/csTXyo/8Sb+afLAkzAptFuMsod9HFokGNudZpi/oQV73hnVK+sR+5PVRMd+Dr7YQ==\\\",\\n      \\\"license\\\": \\\"ISC\\\",\\n      \\\"dependencies\\\": {\\n        \\\"string-width\\\": \\\"^4.2.0\\\",\\n        \\\"strip-ansi\\\": \\\"^6.0.1\\\",\\n        \\\"wrap-ansi\\\": \\\"^7.0.0\\\"\\n      },\\n      \\\"engines\\\": {\\n        \\\"node\\\": \\\">=12\\\"\\n      }\\n    },\\n    \\\"node_modules/color-convert\\\": {\\n      \\\"version\\\": \\\"2.0.1\\\",\\n      \\\"resolved\\\": \\\"https://registry.npmjs.org/color-convert/-/color-convert-2.0.1.tgz\\\",\\n      \\\"integrity\\\": \\\"sha512-RRECPsj7iu/xb5oKYcsFHSppFNnsj/52OVTRKb4zP5onXwVF3zVmmToNcOfGC+CRDpfK/U584fMg38ZHCaElKQ==\\\",\\n      \\\"license\\\": \\\"MIT\\\",\\n      \\\"dependencies\\\": {\\n        \\\"color-name\\\": \\\"~1.1.4\\\"\\n      },\\n      \\\"engines\\\": {\\n        \\\"node\\\": \\\">=7.0.0\\\"\\n      }\\n    },\\n    \\\"node_modules/color-name\\\": {\\n      \\\"version\\\": \\\"1.1.4\\\",\\n      \\\"resolved\\\": \\\"https://registry.npmjs.org/color-name/-/color-name-1.1.4.tgz\\\",\\n      \\\"integrity\\\": \\\"sha512-dOy+3AuW3a2wNbZHIuMZpTcgjGuLU/uBL/ubcZF9OXbDo8ff4O8yVp5Bf0efS8uEoYo5q4Fx7dY9OgQGXgAsQA==\\\",\\n      \\\"license\\\": \\\"MIT\\\"\\n    },\\n    \\\"node_modules/emoji-regex\\\": {\\n      \\\"version\\\": \\\"8.0.0\\\",\\n      \\\"resolved\\\": \\\"https://registry.npmjs.org/emoji-regex/-/emoji-regex-8.0.0.tgz\\\",\\n      \\\"integrity\\\": \\\"sha512-MSjYzcWNOA0ewAHpz0MxpYFvwg6yjy1NG3xteoqz644VCo/RPgnr1/GGt+ic3iJTzQ8Eu3TdM14SawnVUmGE6A==\\\",\\n      \\\"license\\\": \\\"MIT\\\"\\n    },\\n    \\\"node_modules/escalade\\\": {\\n      \\\"version\\\": \\\"3.2.0\\\",\\n      \\\"resolved\\\": \\\"https://registry.npmjs.org/escalade/-/escalade-3.2.0.tgz\\\",\\n      \\\"integrity\\\": \\\"sha512-WUj2qlxaQtO4g6Pq5c29GTcWGDyd8itL8zTlipgECz3JesAiiOKotd8JU6otB3PACgG6xkJUyVhboMS+bje/jA==\\\",\\n      \\\"license\\\": \\\"MIT\\\",\\n      \\\"engines\\\": {\\n        \\\"node\\\": \\\">=6\\\"\\n      }\\n    },\\n    \\\"node_modules/get-caller-file\\\": {\\n      \\\"version\\\": \\\"2.0.5\\\",\\n      \\\"resolved\\\": \\\"https://registry.npmjs.org/get-caller-file/-/get-caller-file-2.0.5.tgz\\\",\\n      \\\"integrity\\\": \\\"sha512-DyFP3BM/3YHTQOCUL/w0OZHR0lpKeGrxotcHWcqNEdnltqFwXVfhEBQ94eIo34AfQpo0rGki4cyIiftY06h2Fg==\\\",\\n      \\\"license\\\": \\\"ISC\\\",\\n      \\\"engines\\\": {\\n        \\\"node\\\": \\\"6.* || 8.* || >= 10.*\\\"\\n      }\\n    },\\n    \\\"node_modules/is-fullwidth-code-point\\\": {\\n      \\\"version\\\": \\\"3.0.0\\\",\\n      \\\"resolved\\\": \\\"https://registry.npmjs.org/is-fullwidth-code-point/-/is-fullwidth-code-point-3.0.0.tgz\\\",\\n      \\\"integrity\\\": \\\"sha512-zymm5+u+sCsSWyD9qNaejV3DFvhCKclKdizYaJUuHA83RLjb7nSuGnddCHGv0hk+KY7BMAlsWeK4Ueg6EV6XQg==\\\",\\n      \\\"license\\\": \\\"MIT\\\",\\n      \\\"engines\\\": {\\n        \\\"node\\\": \\\">=8\\\"\\n      }\\n    },\\n    \\\"node_modules/require-directory\\\": {\\n      \\\"version\\\": \\\"2.1.1\\\",\\n      \\\"resolved\\\": \\\"https://registry.npmjs.org/require-directory/-/require-directory-2.1.1.tgz\\\",\\n      \\\"integrity\\\": \\\"sha512-fGxEI7+wsG9xrvdjsrlmL22OMTTiHRwAMroiEeMgq8gzoLC/PQr7RsRDSTLUg/bZAZtF+TVIkHc6/4RIKrui+Q==\\\",\\n      \\\"license\\\": \\\"MIT\\\",\\n      \\\"engines\\\": {\\n        \\\"node\\\": \\\">=0.10.0\\\"\\n      }\\n    },\\n    \\\"node_modules/string-width\\\": {\\n      \\\"version\\\": \\\"4.2.3\\\",\\n      \\\"resolved\\\": \\\"https://registry.npmjs.org/string-width/-/string-width-4.2.3.tgz\\\",\\n      \\\"integrity\\\": \\\"sha512-wKyQRQpjJ0sIp62ErSZdGsjMJWsap5oRNihHhu6G7JVO/9jIB6UyevL+tXuOqrng8j/cxKTWyWUwvSTriiZz/g==\\\",\\n      \\\"license\\\": \\\"MIT\\\",\\n      \\\"dependencies\\\": {\\n        \\\"emoji-regex\\\": \\\"^8.0.0\\\",\\n        \\\"is-fullwidth-code-point\\\": \\\"^3.0.0\\\",\\n        \\\"strip-ansi\\\": \\\"^6.0.1\\\"\\n      },\\n      \\\"engines\\\": {\\n        \\\"node\\\": \\\">=8\\\"\\n      }\\n    },\\n    \\\"node_modules/strip-ansi\\\": {\\n      \\\"version\\\": \\\"6.0.1\\\",\\n      \\\"resolved\\\": \\\"https://registry.npmjs.org/strip-ansi/-/strip-ansi-6.0.1.tgz\\\",\\n      \\\"integrity\\\": \\\"sha512-Y38VPSHcqkFrCpFnQ9vuSXmquuv5oXOKpGeT6aGrr3o3Gc9AlVa6JBfUSOCnbxGGZF+/0ooI7KrPuUSztUdU5A==\\\",\\n      \\\"license\\\": \\\"MIT\\\",\\n      \\\"dependencies\\\": {\\n        \\\"ansi-regex\\\": \\\"^5.0.1\\\"\\n      },\\n      \\\"engines\\\": {\\n        \\\"node\\\": \\\">=8\\\"\\n      }\\n    },\\n    \\\"node_modules/typescript\\\": {\\n      \\\"version\\\": \\\"5.7.3\\\",\\n      \\\"resolved\\\": \\\"https://registry.npmjs.org/typescript/-/typescript-5.7.3.tgz\\\",\\n      \\\"integrity\\\": \\\"sha512-84MVSjMEHP+FQRPy3pX9sTVV/INIex71s9TL2Gm5FG/WG1SqXeKyZ0k7/blY/4FdOzI12CBy1vGc4og/eus0fw==\\\",\\n      \\\"dev\\\": true,\\n      \\\"license\\\": \\\"Apache-2.0\\\",\\n      \\\"bin\\\": {\\n        \\\"tsc\\\": \\\"bin/tsc\\\",\\n        \\\"tsserver\\\": \\\"bin/tsserver\\\"\\n      },\\n      \\\"engines\\\": {\\n        \\\"node\\\": \\\">=14.17\\\"\\n      }\\n    },\\n    \\\"node_modules/undici-types\\\": {\\n      \\\"version\\\": \\\"6.20.0\\\",\\n      \\\"resolved\\\": \\\"https://registry.npmjs.org/undici-types/-/undici-types-6.20.0.tgz\\\",\\n      \\\"integrity\\\": \\\"sha512-Ny6QZ2Nju20vw1SRHe3d9jVu6gJ+4e3+MMpqu7pqE5HT6WsTSlce++GQmK5UXS8mzV8DSYHrQH+Xrf2jVcuKNg==\\\",\\n      \\\"dev\\\": true,\\n      \\\"license\\\": \\\"MIT\\\"\\n    },\\n    \\\"node_modules/wrap-ansi\\\": {\\n      \\\"version\\\": \\\"7.0.0\\\",\\n      \\\"resolved\\\": \\\"https://registry.npmjs.org/wrap-ansi/-/wrap-ansi-7.0.0.tgz\\\",\\n      \\\"integrity\\\": \\\"sha512-YVGIj2kamLSTxw6NsZjoBxfSwsn0ycdesmc4p+Q21c5zPuZ1pl+NfxVdxPtdHvmNVOQ6XSYG4AUtyt/Fi7D16Q==\\\",\\n      \\\"license\\\": \\\"MIT\\\",\\n      \\\"dependencies\\\": {\\n        \\\"ansi-styles\\\": \\\"^4.0.0\\\",\\n        \\\"string-width\\\": \\\"^4.1.0\\\",\\n        \\\"strip-ansi\\\": \\\"^6.0.0\\\"\\n      },\\n      \\\"engines\\\": {\\n        \\\"node\\\": \\\">=10\\\"\\n      },\\n      \\\"funding\\\": {\\n        \\\"url\\\": \\\"https://github.com/chalk/wrap-ansi?sponsor=1\\\"\\n      }\\n    },\\n    \\\"node_modules/y18n\\\": {\\n      \\\"version\\\": \\\"5.0.8\\\",\\n      \\\"resolved\\\": \\\"https://registry.npmjs.org/y18n/-/y18n-5.0.8.tgz\\\",\\n      \\\"integrity\\\": \\\"sha512-0pfFzegeDWJHJIAmTLRP2DwHjdF5s7jo9tuztdQxAhINCdvS+3nGINqPd00AphqJR/0LhANUS6/+7SCb98YOfA==\\\",\\n      \\\"license\\\": \\\"ISC\\\",\\n      \\\"engines\\\": {\\n        \\\"node\\\": \\\">=10\\\"\\n      }\\n    },\\n    \\\"node_modules/yargs\\\": {\\n      \\\"version\\\": \\\"17.7.2\\\",\\n      \\\"resolved\\\": \\\"https://registry.npmjs.org/yargs/-/yargs-17.7.2.tgz\\\",\\n      \\\"integrity\\\": \\\"sha512-7dSzzRQ++CKnNI/krKnYRV7JKKPUXMEh61soaHKg9mrWEhzFWhFnxPxGl+69cD1Ou63C13NUPCnmIcrvqCuM6w==\\\",\\n      \\\"license\\\": \\\"MIT\\\",\\n      \\\"dependencies\\\": {\\n        \\\"cliui\\\": \\\"^8.0.1\\\",\\n        \\\"escalade\\\": \\\"^3.1.1\\\",\\n        \\\"get-caller-file\\\": \\\"^2.0.5\\\",\\n        \\\"require-directory\\\": \\\"^2.1.1\\\",\\n        \\\"string-width\\\": \\\"^4.2.3\\\",\\n        \\\"y18n\\\": \\\"^5.0.5\\\",\\n        \\\"yargs-parser\\\": \\\"^21.1.1\\\"\\n      },\\n      \\\"engines\\\": {\\n        \\\"node\\\": \\\">=12\\\"\\n      }\\n    },\\n    \\\"node_modules/yargs-parser\\\": {\\n      \\\"version\\\": \\\"21.1.1\\\",\\n      \\\"resolved\\\": \\\"https://registry.npmjs.org/yargs-parser/-/yargs-parser-21.1.1.tgz\\\",\\n      \\\"integrity\\\": \\\"sha512-tVpsJW7DdjecAiFpbIB1e3qxIQsE6NoPc5/eTdrbbIC4h0LVsWhnoa3g+m2HclBIujHzsxZ4VJVA+GUuc2/LBw==\\\",\\n      \\\"license\\\": \\\"ISC\\\",\\n      \\\"engines\\\": {\\n        \\\"node\\\": \\\">=12\\\"\\n      }\\n    }\\n  }\\n}\\n\"\n  },\n  \"package.json\": {\n    \"path\": \"package.json\",\n    \"content\": \"{\\n  \\\"name\\\": \\\"source-collector\\\",\\n  \\\"version\\\": \\\"0.0.1\\\",\\n  \\\"description\\\": \\\"Utility to collect file content and generate output in txt or json format\\\",\\n  \\\"main\\\": \\\"dist/index.js\\\",\\n  \\\"bin\\\": {\\n    \\\"file-collector\\\": \\\"dist/cli.js\\\"\\n  },\\n  \\\"scripts\\\": {\\n    \\\"build\\\": \\\"tsc\\\",\\n    \\\"test\\\": \\\"echo \\\\\\\"No tests yet\\\\\\\"\\\",\\n    \\\"start\\\": \\\"node dist/index.js\\\"\\n  },\\n  \\\"keywords\\\": [\\n    \\\"file\\\",\\n    \\\"utility\\\",\\n    \\\"cli\\\",\\n    \\\"json\\\",\\n    \\\"txt\\\"\\n  ],\\n  \\\"author\\\": \\\"BroBobro\\\",\\n  \\\"license\\\": \\\"MIT\\\",\\n  \\\"dependencies\\\": {\\n    \\\"yargs\\\": \\\"^17.7.2\\\"\\n  },\\n  \\\"devDependencies\\\": {\\n    \\\"@types/node\\\": \\\"^22.10.10\\\",\\n    \\\"@types/yargs\\\": \\\"^17.0.33\\\",\\n    \\\"typescript\\\": \\\"^5.2.0\\\"\\n  }\\n}\\n\"\n  },\n  \"tsconfig.json\": {\n    \"path\": \"tsconfig.json\",\n    \"content\": \"{\\n  \\\"compilerOptions\\\": {\\n    \\\"target\\\": \\\"ES2020\\\",\\n    \\\"module\\\": \\\"CommonJS\\\",\\n    \\\"outDir\\\": \\\"./dist\\\",\\n    \\\"strict\\\": true,\\n    \\\"esModuleInterop\\\": true,\\n    \\\"resolveJsonModule\\\": true,\\n    \\\"skipLibCheck\\\": true,\\n    \\\"types\\\": [\\\"node\\\"]\\n  },\\n  \\\"include\\\": [\\\"src/**/*\\\"]\\n}\\n\"\n  },\n  \"yarn.lock\": {\n    \"path\": \"yarn.lock\",\n    \"content\": \"# THIS IS AN AUTOGENERATED FILE. DO NOT EDIT THIS FILE DIRECTLY.\\n# yarn lockfile v1\\n\\n\\n\\\"@types/node@^22.10.10\\\":\\n  version \\\"22.10.10\\\"\\n  resolved \\\"https://registry.npmjs.org/@types/node/-/node-22.10.10.tgz\\\"\\n  integrity sha512-X47y/mPNzxviAGY5TcYPtYL8JsY3kAq2n8fMmKoRCxq/c4v4pyGNCzM2R6+M5/umG4ZfHuT+sgqDYqWc9rJ6ww==\\n  dependencies:\\n    undici-types \\\"~6.20.0\\\"\\n\\n\\\"@types/yargs-parser@*\\\":\\n  version \\\"21.0.3\\\"\\n  resolved \\\"https://registry.npmjs.org/@types/yargs-parser/-/yargs-parser-21.0.3.tgz\\\"\\n  integrity sha512-I4q9QU9MQv4oEOz4tAHJtNz1cwuLxn2F3xcc2iV5WdqLPpUnj30aUuxt1mAxYTG+oe8CZMV/+6rU4S4gRDzqtQ==\\n\\n\\\"@types/yargs@^17.0.33\\\":\\n  version \\\"17.0.33\\\"\\n  resolved \\\"https://registry.npmjs.org/@types/yargs/-/yargs-17.0.33.tgz\\\"\\n  integrity sha512-WpxBCKWPLr4xSsHgz511rFJAM+wS28w2zEO1QDNY5zM/S8ok70NNfztH0xwhqKyaK0OHCbN98LDAZuy1ctxDkA==\\n  dependencies:\\n    \\\"@types/yargs-parser\\\" \\\"*\\\"\\n\\nansi-regex@^5.0.1:\\n  version \\\"5.0.1\\\"\\n  resolved \\\"https://registry.npmjs.org/ansi-regex/-/ansi-regex-5.0.1.tgz\\\"\\n  integrity sha512-quJQXlTSUGL2LH9SUXo8VwsY4soanhgo6LNSm84E1LBcE8s3O0wpdiRzyR9z/ZZJMlMWv37qOOb9pdJlMUEKFQ==\\n\\nansi-styles@^4.0.0:\\n  version \\\"4.3.0\\\"\\n  resolved \\\"https://registry.npmjs.org/ansi-styles/-/ansi-styles-4.3.0.tgz\\\"\\n  integrity sha512-zbB9rCJAT1rbjiVDb2hqKFHNYLxgtk8NURxZ3IZwD3F6NtxbXZQCnnSi1Lkx+IDohdPlFp222wVALIheZJQSEg==\\n  dependencies:\\n    color-convert \\\"^2.0.1\\\"\\n\\ncliui@^8.0.1:\\n  version \\\"8.0.1\\\"\\n  resolved \\\"https://registry.npmjs.org/cliui/-/cliui-8.0.1.tgz\\\"\\n  integrity sha512-BSeNnyus75C4//NQ9gQt1/csTXyo/8Sb+afLAkzAptFuMsod9HFokGNudZpi/oQV73hnVK+sR+5PVRMd+Dr7YQ==\\n  dependencies:\\n    string-width \\\"^4.2.0\\\"\\n    strip-ansi \\\"^6.0.1\\\"\\n    wrap-ansi \\\"^7.0.0\\\"\\n\\ncolor-convert@^2.0.1:\\n  version \\\"2.0.1\\\"\\n  resolved \\\"https://registry.npmjs.org/color-convert/-/color-convert-2.0.1.tgz\\\"\\n  integrity sha512-RRECPsj7iu/xb5oKYcsFHSppFNnsj/52OVTRKb4zP5onXwVF3zVmmToNcOfGC+CRDpfK/U584fMg38ZHCaElKQ==\\n  dependencies:\\n    color-name \\\"~1.1.4\\\"\\n\\ncolor-name@~1.1.4:\\n  version \\\"1.1.4\\\"\\n  resolved \\\"https://registry.npmjs.org/color-name/-/color-name-1.1.4.tgz\\\"\\n  integrity sha512-dOy+3AuW3a2wNbZHIuMZpTcgjGuLU/uBL/ubcZF9OXbDo8ff4O8yVp5Bf0efS8uEoYo5q4Fx7dY9OgQGXgAsQA==\\n\\nemoji-regex@^8.0.0:\\n  version \\\"8.0.0\\\"\\n  resolved \\\"https://registry.npmjs.org/emoji-regex/-/emoji-regex-8.0.0.tgz\\\"\\n  integrity sha512-MSjYzcWNOA0ewAHpz0MxpYFvwg6yjy1NG3xteoqz644VCo/RPgnr1/GGt+ic3iJTzQ8Eu3TdM14SawnVUmGE6A==\\n\\nescalade@^3.1.1:\\n  version \\\"3.2.0\\\"\\n  resolved \\\"https://registry.npmjs.org/escalade/-/escalade-3.2.0.tgz\\\"\\n  integrity sha512-WUj2qlxaQtO4g6Pq5c29GTcWGDyd8itL8zTlipgECz3JesAiiOKotd8JU6otB3PACgG6xkJUyVhboMS+bje/jA==\\n\\nget-caller-file@^2.0.5:\\n  version \\\"2.0.5\\\"\\n  resolved \\\"https://registry.npmjs.org/get-caller-file/-/get-caller-file-2.0.5.tgz\\\"\\n  integrity sha512-DyFP3BM/3YHTQOCUL/w0OZHR0lpKeGrxotcHWcqNEdnltqFwXVfhEBQ94eIo34AfQpo0rGki4cyIiftY06h2Fg==\\n\\nis-fullwidth-code-point@^3.0.0:\\n  version \\\"3.0.0\\\"\\n  resolved \\\"https://registry.npmjs.org/is-fullwidth-code-point/-/is-fullwidth-code-point-3.0.0.tgz\\\"\\n  integrity sha512-zymm5+u+sCsSWyD9qNaejV3DFvhCKclKdizYaJUuHA83RLjb7nSuGnddCHGv0hk+KY7BMAlsWeK4Ueg6EV6XQg==\\n\\nrequire-directory@^2.1.1:\\n  version \\\"2.1.1\\\"\\n  resolved \\\"https://registry.npmjs.org/require-directory/-/require-directory-2.1.1.tgz\\\"\\n  integrity sha512-fGxEI7+wsG9xrvdjsrlmL22OMTTiHRwAMroiEeMgq8gzoLC/PQr7RsRDSTLUg/bZAZtF+TVIkHc6/4RIKrui+Q==\\n\\nstring-width@^4.1.0, string-width@^4.2.0, string-width@^4.2.3:\\n  version \\\"4.2.3\\\"\\n  resolved \\\"https://registry.npmjs.org/string-width/-/string-width-4.2.3.tgz\\\"\\n  integrity sha512-wKyQRQpjJ0sIp62ErSZdGsjMJWsap5oRNihHhu6G7JVO/9jIB6UyevL+tXuOqrng8j/cxKTWyWUwvSTriiZz/g==\\n  dependencies:\\n    emoji-regex \\\"^8.0.0\\\"\\n    is-fullwidth-code-point \\\"^3.0.0\\\"\\n    strip-ansi \\\"^6.0.1\\\"\\n\\nstrip-ansi@^6.0.0, strip-ansi@^6.0.1:\\n  version \\\"6.0.1\\\"\\n  resolved \\\"https://registry.npmjs.org/strip-ansi/-/strip-ansi-6.0.1.tgz\\\"\\n  integrity sha512-Y38VPSHcqkFrCpFnQ9vuSXmquuv5oXOKpGeT6aGrr3o3Gc9AlVa6JBfUSOCnbxGGZF+/0ooI7KrPuUSztUdU5A==\\n  dependencies:\\n    ansi-regex \\\"^5.0.1\\\"\\n\\ntypescript@^5.2.0:\\n  version \\\"5.7.3\\\"\\n  resolved \\\"https://registry.npmjs.org/typescript/-/typescript-5.7.3.tgz\\\"\\n  integrity sha512-84MVSjMEHP+FQRPy3pX9sTVV/INIex71s9TL2Gm5FG/WG1SqXeKyZ0k7/blY/4FdOzI12CBy1vGc4og/eus0fw==\\n\\nundici-types@~6.20.0:\\n  version \\\"6.20.0\\\"\\n  resolved \\\"https://registry.npmjs.org/undici-types/-/undici-types-6.20.0.tgz\\\"\\n  integrity sha512-Ny6QZ2Nju20vw1SRHe3d9jVu6gJ+4e3+MMpqu7pqE5HT6WsTSlce++GQmK5UXS8mzV8DSYHrQH+Xrf2jVcuKNg==\\n\\nwrap-ansi@^7.0.0:\\n  version \\\"7.0.0\\\"\\n  resolved \\\"https://registry.npmjs.org/wrap-ansi/-/wrap-ansi-7.0.0.tgz\\\"\\n  integrity sha512-YVGIj2kamLSTxw6NsZjoBxfSwsn0ycdesmc4p+Q21c5zPuZ1pl+NfxVdxPtdHvmNVOQ6XSYG4AUtyt/Fi7D16Q==\\n  dependencies:\\n    ansi-styles \\\"^4.0.0\\\"\\n    string-width \\\"^4.1.0\\\"\\n    strip-ansi \\\"^6.0.0\\\"\\n\\ny18n@^5.0.5:\\n  version \\\"5.0.8\\\"\\n  resolved \\\"https://registry.npmjs.org/y18n/-/y18n-5.0.8.tgz\\\"\\n  integrity sha512-0pfFzegeDWJHJIAmTLRP2DwHjdF5s7jo9tuztdQxAhINCdvS+3nGINqPd00AphqJR/0LhANUS6/+7SCb98YOfA==\\n\\nyargs-parser@^21.1.1:\\n  version \\\"21.1.1\\\"\\n  resolved \\\"https://registry.npmjs.org/yargs-parser/-/yargs-parser-21.1.1.tgz\\\"\\n  integrity sha512-tVpsJW7DdjecAiFpbIB1e3qxIQsE6NoPc5/eTdrbbIC4h0LVsWhnoa3g+m2HclBIujHzsxZ4VJVA+GUuc2/LBw==\\n\\nyargs@^17.7.2:\\n  version \\\"17.7.2\\\"\\n  resolved \\\"https://registry.npmjs.org/yargs/-/yargs-17.7.2.tgz\\\"\\n  integrity sha512-7dSzzRQ++CKnNI/krKnYRV7JKKPUXMEh61soaHKg9mrWEhzFWhFnxPxGl+69cD1Ou63C13NUPCnmIcrvqCuM6w==\\n  dependencies:\\n    cliui \\\"^8.0.1\\\"\\n    escalade \\\"^3.1.1\\\"\\n    get-caller-file \\\"^2.0.5\\\"\\n    require-directory \\\"^2.1.1\\\"\\n    string-width \\\"^4.2.3\\\"\\n    y18n \\\"^5.0.5\\\"\\n    yargs-parser \\\"^21.1.1\\\"\\n\"\n  }\n}"
  },
  "package-lock.json": {
    "path": "package-lock.json",
    "content": "{\n  \"name\": \"source-collector\",\n  \"version\": \"0.0.1\",\n  \"lockfileVersion\": 3,\n  \"requires\": true,\n  \"packages\": {\n    \"\": {\n      \"name\": \"source-collector\",\n      \"version\": \"0.0.1\",\n      \"license\": \"MIT\",\n      \"dependencies\": {\n        \"yargs\": \"^17.7.2\"\n      },\n      \"bin\": {\n        \"file-collector\": \"dist/cli.js\"\n      },\n      \"devDependencies\": {\n        \"@types/node\": \"^22.10.10\",\n        \"@types/yargs\": \"^17.0.33\",\n        \"typescript\": \"^5.2.0\"\n      }\n    },\n    \"node_modules/@types/node\": {\n      \"version\": \"22.10.10\",\n      \"resolved\": \"https://registry.npmjs.org/@types/node/-/node-22.10.10.tgz\",\n      \"integrity\": \"sha512-X47y/mPNzxviAGY5TcYPtYL8JsY3kAq2n8fMmKoRCxq/c4v4pyGNCzM2R6+M5/umG4ZfHuT+sgqDYqWc9rJ6ww==\",\n      \"dev\": true,\n      \"license\": \"MIT\",\n      \"dependencies\": {\n        \"undici-types\": \"~6.20.0\"\n      }\n    },\n    \"node_modules/@types/yargs\": {\n      \"version\": \"17.0.33\",\n      \"resolved\": \"https://registry.npmjs.org/@types/yargs/-/yargs-17.0.33.tgz\",\n      \"integrity\": \"sha512-WpxBCKWPLr4xSsHgz511rFJAM+wS28w2zEO1QDNY5zM/S8ok70NNfztH0xwhqKyaK0OHCbN98LDAZuy1ctxDkA==\",\n      \"dev\": true,\n      \"license\": \"MIT\",\n      \"dependencies\": {\n        \"@types/yargs-parser\": \"*\"\n      }\n    },\n    \"node_modules/@types/yargs-parser\": {\n      \"version\": \"21.0.3\",\n      \"resolved\": \"https://registry.npmjs.org/@types/yargs-parser/-/yargs-parser-21.0.3.tgz\",\n      \"integrity\": \"sha512-I4q9QU9MQv4oEOz4tAHJtNz1cwuLxn2F3xcc2iV5WdqLPpUnj30aUuxt1mAxYTG+oe8CZMV/+6rU4S4gRDzqtQ==\",\n      \"dev\": true,\n      \"license\": \"MIT\"\n    },\n    \"node_modules/ansi-regex\": {\n      \"version\": \"5.0.1\",\n      \"resolved\": \"https://registry.npmjs.org/ansi-regex/-/ansi-regex-5.0.1.tgz\",\n      \"integrity\": \"sha512-quJQXlTSUGL2LH9SUXo8VwsY4soanhgo6LNSm84E1LBcE8s3O0wpdiRzyR9z/ZZJMlMWv37qOOb9pdJlMUEKFQ==\",\n      \"license\": \"MIT\",\n      \"engines\": {\n        \"node\": \">=8\"\n      }\n    },\n    \"node_modules/ansi-styles\": {\n      \"version\": \"4.3.0\",\n      \"resolved\": \"https://registry.npmjs.org/ansi-styles/-/ansi-styles-4.3.0.tgz\",\n      \"integrity\": \"sha512-zbB9rCJAT1rbjiVDb2hqKFHNYLxgtk8NURxZ3IZwD3F6NtxbXZQCnnSi1Lkx+IDohdPlFp222wVALIheZJQSEg==\",\n      \"license\": \"MIT\",\n      \"dependencies\": {\n        \"color-convert\": \"^2.0.1\"\n      },\n      \"engines\": {\n        \"node\": \">=8\"\n      },\n      \"funding\": {\n        \"url\": \"https://github.com/chalk/ansi-styles?sponsor=1\"\n      }\n    },\n    \"node_modules/cliui\": {\n      \"version\": \"8.0.1\",\n      \"resolved\": \"https://registry.npmjs.org/cliui/-/cliui-8.0.1.tgz\",\n      \"integrity\": \"sha512-BSeNnyus75C4//NQ9gQt1/csTXyo/8Sb+afLAkzAptFuMsod9HFokGNudZpi/oQV73hnVK+sR+5PVRMd+Dr7YQ==\",\n      \"license\": \"ISC\",\n      \"dependencies\": {\n        \"string-width\": \"^4.2.0\",\n        \"strip-ansi\": \"^6.0.1\",\n        \"wrap-ansi\": \"^7.0.0\"\n      },\n      \"engines\": {\n        \"node\": \">=12\"\n      }\n    },\n    \"node_modules/color-convert\": {\n      \"version\": \"2.0.1\",\n      \"resolved\": \"https://registry.npmjs.org/color-convert/-/color-convert-2.0.1.tgz\",\n      \"integrity\": \"sha512-RRECPsj7iu/xb5oKYcsFHSppFNnsj/52OVTRKb4zP5onXwVF3zVmmToNcOfGC+CRDpfK/U584fMg38ZHCaElKQ==\",\n      \"license\": \"MIT\",\n      \"dependencies\": {\n        \"color-name\": \"~1.1.4\"\n      },\n      \"engines\": {\n        \"node\": \">=7.0.0\"\n      }\n    },\n    \"node_modules/color-name\": {\n      \"version\": \"1.1.4\",\n      \"resolved\": \"https://registry.npmjs.org/color-name/-/color-name-1.1.4.tgz\",\n      \"integrity\": \"sha512-dOy+3AuW3a2wNbZHIuMZpTcgjGuLU/uBL/ubcZF9OXbDo8ff4O8yVp5Bf0efS8uEoYo5q4Fx7dY9OgQGXgAsQA==\",\n      \"license\": \"MIT\"\n    },\n    \"node_modules/emoji-regex\": {\n      \"version\": \"8.0.0\",\n      \"resolved\": \"https://registry.npmjs.org/emoji-regex/-/emoji-regex-8.0.0.tgz\",\n      \"integrity\": \"sha512-MSjYzcWNOA0ewAHpz0MxpYFvwg6yjy1NG3xteoqz644VCo/RPgnr1/GGt+ic3iJTzQ8Eu3TdM14SawnVUmGE6A==\",\n      \"license\": \"MIT\"\n    },\n    \"node_modules/escalade\": {\n      \"version\": \"3.2.0\",\n      \"resolved\": \"https://registry.npmjs.org/escalade/-/escalade-3.2.0.tgz\",\n      \"integrity\": \"sha512-WUj2qlxaQtO4g6Pq5c29GTcWGDyd8itL8zTlipgECz3JesAiiOKotd8JU6otB3PACgG6xkJUyVhboMS+bje/jA==\",\n      \"license\": \"MIT\",\n      \"engines\": {\n        \"node\": \">=6\"\n      }\n    },\n    \"node_modules/get-caller-file\": {\n      \"version\": \"2.0.5\",\n      \"resolved\": \"https://registry.npmjs.org/get-caller-file/-/get-caller-file-2.0.5.tgz\",\n      \"integrity\": \"sha512-DyFP3BM/3YHTQOCUL/w0OZHR0lpKeGrxotcHWcqNEdnltqFwXVfhEBQ94eIo34AfQpo0rGki4cyIiftY06h2Fg==\",\n      \"license\": \"ISC\",\n      \"engines\": {\n        \"node\": \"6.* || 8.* || >= 10.*\"\n      }\n    },\n    \"node_modules/is-fullwidth-code-point\": {\n      \"version\": \"3.0.0\",\n      \"resolved\": \"https://registry.npmjs.org/is-fullwidth-code-point/-/is-fullwidth-code-point-3.0.0.tgz\",\n      \"integrity\": \"sha512-zymm5+u+sCsSWyD9qNaejV3DFvhCKclKdizYaJUuHA83RLjb7nSuGnddCHGv0hk+KY7BMAlsWeK4Ueg6EV6XQg==\",\n      \"license\": \"MIT\",\n      \"engines\": {\n        \"node\": \">=8\"\n      }\n    },\n    \"node_modules/require-directory\": {\n      \"version\": \"2.1.1\",\n      \"resolved\": \"https://registry.npmjs.org/require-directory/-/require-directory-2.1.1.tgz\",\n      \"integrity\": \"sha512-fGxEI7+wsG9xrvdjsrlmL22OMTTiHRwAMroiEeMgq8gzoLC/PQr7RsRDSTLUg/bZAZtF+TVIkHc6/4RIKrui+Q==\",\n      \"license\": \"MIT\",\n      \"engines\": {\n        \"node\": \">=0.10.0\"\n      }\n    },\n    \"node_modules/string-width\": {\n      \"version\": \"4.2.3\",\n      \"resolved\": \"https://registry.npmjs.org/string-width/-/string-width-4.2.3.tgz\",\n      \"integrity\": \"sha512-wKyQRQpjJ0sIp62ErSZdGsjMJWsap5oRNihHhu6G7JVO/9jIB6UyevL+tXuOqrng8j/cxKTWyWUwvSTriiZz/g==\",\n      \"license\": \"MIT\",\n      \"dependencies\": {\n        \"emoji-regex\": \"^8.0.0\",\n        \"is-fullwidth-code-point\": \"^3.0.0\",\n        \"strip-ansi\": \"^6.0.1\"\n      },\n      \"engines\": {\n        \"node\": \">=8\"\n      }\n    },\n    \"node_modules/strip-ansi\": {\n      \"version\": \"6.0.1\",\n      \"resolved\": \"https://registry.npmjs.org/strip-ansi/-/strip-ansi-6.0.1.tgz\",\n      \"integrity\": \"sha512-Y38VPSHcqkFrCpFnQ9vuSXmquuv5oXOKpGeT6aGrr3o3Gc9AlVa6JBfUSOCnbxGGZF+/0ooI7KrPuUSztUdU5A==\",\n      \"license\": \"MIT\",\n      \"dependencies\": {\n        \"ansi-regex\": \"^5.0.1\"\n      },\n      \"engines\": {\n        \"node\": \">=8\"\n      }\n    },\n    \"node_modules/typescript\": {\n      \"version\": \"5.7.3\",\n      \"resolved\": \"https://registry.npmjs.org/typescript/-/typescript-5.7.3.tgz\",\n      \"integrity\": \"sha512-84MVSjMEHP+FQRPy3pX9sTVV/INIex71s9TL2Gm5FG/WG1SqXeKyZ0k7/blY/4FdOzI12CBy1vGc4og/eus0fw==\",\n      \"dev\": true,\n      \"license\": \"Apache-2.0\",\n      \"bin\": {\n        \"tsc\": \"bin/tsc\",\n        \"tsserver\": \"bin/tsserver\"\n      },\n      \"engines\": {\n        \"node\": \">=14.17\"\n      }\n    },\n    \"node_modules/undici-types\": {\n      \"version\": \"6.20.0\",\n      \"resolved\": \"https://registry.npmjs.org/undici-types/-/undici-types-6.20.0.tgz\",\n      \"integrity\": \"sha512-Ny6QZ2Nju20vw1SRHe3d9jVu6gJ+4e3+MMpqu7pqE5HT6WsTSlce++GQmK5UXS8mzV8DSYHrQH+Xrf2jVcuKNg==\",\n      \"dev\": true,\n      \"license\": \"MIT\"\n    },\n    \"node_modules/wrap-ansi\": {\n      \"version\": \"7.0.0\",\n      \"resolved\": \"https://registry.npmjs.org/wrap-ansi/-/wrap-ansi-7.0.0.tgz\",\n      \"integrity\": \"sha512-YVGIj2kamLSTxw6NsZjoBxfSwsn0ycdesmc4p+Q21c5zPuZ1pl+NfxVdxPtdHvmNVOQ6XSYG4AUtyt/Fi7D16Q==\",\n      \"license\": \"MIT\",\n      \"dependencies\": {\n        \"ansi-styles\": \"^4.0.0\",\n        \"string-width\": \"^4.1.0\",\n        \"strip-ansi\": \"^6.0.0\"\n      },\n      \"engines\": {\n        \"node\": \">=10\"\n      },\n      \"funding\": {\n        \"url\": \"https://github.com/chalk/wrap-ansi?sponsor=1\"\n      }\n    },\n    \"node_modules/y18n\": {\n      \"version\": \"5.0.8\",\n      \"resolved\": \"https://registry.npmjs.org/y18n/-/y18n-5.0.8.tgz\",\n      \"integrity\": \"sha512-0pfFzegeDWJHJIAmTLRP2DwHjdF5s7jo9tuztdQxAhINCdvS+3nGINqPd00AphqJR/0LhANUS6/+7SCb98YOfA==\",\n      \"license\": \"ISC\",\n      \"engines\": {\n        \"node\": \">=10\"\n      }\n    },\n    \"node_modules/yargs\": {\n      \"version\": \"17.7.2\",\n      \"resolved\": \"https://registry.npmjs.org/yargs/-/yargs-17.7.2.tgz\",\n      \"integrity\": \"sha512-7dSzzRQ++CKnNI/krKnYRV7JKKPUXMEh61soaHKg9mrWEhzFWhFnxPxGl+69cD1Ou63C13NUPCnmIcrvqCuM6w==\",\n      \"license\": \"MIT\",\n      \"dependencies\": {\n        \"cliui\": \"^8.0.1\",\n        \"escalade\": \"^3.1.1\",\n        \"get-caller-file\": \"^2.0.5\",\n        \"require-directory\": \"^2.1.1\",\n        \"string-width\": \"^4.2.3\",\n        \"y18n\": \"^5.0.5\",\n        \"yargs-parser\": \"^21.1.1\"\n      },\n      \"engines\": {\n        \"node\": \">=12\"\n      }\n    },\n    \"node_modules/yargs-parser\": {\n      \"version\": \"21.1.1\",\n      \"resolved\": \"https://registry.npmjs.org/yargs-parser/-/yargs-parser-21.1.1.tgz\",\n      \"integrity\": \"sha512-tVpsJW7DdjecAiFpbIB1e3qxIQsE6NoPc5/eTdrbbIC4h0LVsWhnoa3g+m2HclBIujHzsxZ4VJVA+GUuc2/LBw==\",\n      \"license\": \"ISC\",\n      \"engines\": {\n        \"node\": \">=12\"\n      }\n    }\n  }\n}\n"
  },
  "package.json": {
    "path": "package.json",
    "content": "{\n  \"name\": \"source-collector\",\n  \"version\": \"0.0.1\",\n  \"description\": \"Utility to collect file content and generate output in txt or json format\",\n  \"main\": \"dist/index.js\",\n  \"bin\": {\n    \"file-collector\": \"dist/cli.js\"\n  },\n  \"scripts\": {\n    \"build\": \"tsc\",\n    \"test\": \"echo \\\"No tests yet\\\"\",\n    \"start\": \"node dist/index.js\"\n  },\n  \"keywords\": [\n    \"file\",\n    \"utility\",\n    \"cli\",\n    \"json\",\n    \"txt\"\n  ],\n  \"author\": \"BroBobro\",\n  \"license\": \"MIT\",\n  \"dependencies\": {\n    \"yargs\": \"^17.7.2\"\n  },\n  \"devDependencies\": {\n    \"@types/node\": \"^22.10.10\",\n    \"@types/yargs\": \"^17.0.33\",\n    \"typescript\": \"^5.2.0\"\n  }\n}\n"
  },
  "src/cli.ts": {
    "path": "src/cli.ts",
    "content": "#!/usr/bin/env node\nimport { FileCollector } from './fileCollector';\nimport path from 'path';\nimport yargs from 'yargs';\nimport { hideBin } from 'yargs/helpers';\n\n\n\n(async () => {\n  const rootDir = process.cwd();\n  const argv = await yargs(hideBin(process.argv))\n    .option('includeDirs', {\n      type: 'array',\n      description: 'Directories to include',\n    })\n    .option('excludeDirs', {\n      type: 'array',\n      default: ['node_modules'],\n      description: 'Directories to exclude',\n    })\n    .option('outputFormat', {\n      type: 'string',\n      choices: ['txt', 'json'],\n      default: 'json',\n      description: 'Output file format',\n    })\n    .option('outputPath', {\n      type: 'string',\n      default: 'output.txt',\n      description: 'Path to save the output file',\n    })\n    .demandCommand(0)\n    .help()\n    .argv;\n\n  console.log(argv);\n    \n  const collector = new FileCollector(rootDir, {\n    includeDirs: argv.includeDirs as string[],\n    excludeDirs: argv.excludeDirs as string[],\n    outputFormat: argv.outputFormat as 'txt' | 'json',\n  });\n  await collector.saveOutput(path.resolve(argv.outputPath as string));\n})();\n"
  },
  "src/fileCollector.ts": {
    "path": "src/fileCollector.ts",
    "content": "import fs from 'fs';\nimport path from 'path';\n\nexport interface Options {\n  includeDirs?: string[];\n  excludeDirs?: string[];\n  outputFormat?: 'txt' | 'json';\n}\n\nexport class FileCollector {\n  private rootDir: string;\n  private includeDirs: string[];\n  private excludeDirs: string[];\n  private outputFormat: 'txt' | 'json';\n\n  constructor(rootDir: string, options: Options = {}) {\n    this.rootDir = rootDir;\n    this.includeDirs = options.includeDirs || [];\n    this.excludeDirs = options.excludeDirs || ['node_modules'];\n    this.outputFormat = options.outputFormat || 'json';\n  }\n\n  private async collectFiles(dir: string): Promise<string[]> {\n    const files: string[] = [];\n    const entries = await fs.promises.readdir(dir, { withFileTypes: true });\n\n    for (const entry of entries) {\n      const fullPath = path.join(dir, entry.name);\n\n      if (entry.isDirectory()) {\n        const relativePath = path.relative(this.rootDir, fullPath);\n        if (\n          !this.excludeDirs.includes(relativePath)\n        ) {\n          files.push(...(await this.collectFiles(fullPath)));\n        }\n      } else {\n        files.push(fullPath);\n      }\n    }\n    return files;\n  }\n\n  private async generateTxt(files: string[]): Promise<string> {\n    return files\n      .map((file) => {\n        const content = fs.readFileSync(file, 'utf-8');\n        const relativePath = path.relative(this.rootDir, file);\n        \n        return `__FILE_PATH__\\n${relativePath}\\n__FILE_CONTENT__\\n${content}\\n__END_OF_FILE__`;\n      })\n      .join('\\n');\n  }\n\n  private async generateJson(files: string[]): Promise<Record<string, { path: string; content: string }>> {\n    const output: Record<string, { path: string; content: string }> = {};\n    for (const file of files) {\n      const content = fs.readFileSync(file, 'utf-8');\n      \n      const relativePath = path.relative(this.rootDir, file);\n      output[relativePath] = { path: relativePath, content };\n    }\n    return output;\n  }\n\n  public async generateOutput(): Promise<string | Record<string, any>> {\n    const files = await this.collectFiles(this.rootDir);\n    if (this.outputFormat === 'txt') {\n      return this.generateTxt(files);\n    } else {\n      return this.generateJson(files);\n    }\n  }\n\n  public async saveOutput(outputPath: string): Promise<void> {\n    const output = await this.generateOutput();\n    \n    if (this.outputFormat === 'txt') {\n      fs.writeFileSync(outputPath, output as string, 'utf-8');\n    } else {\n      fs.writeFileSync(outputPath, JSON.stringify(output, null, 2), 'utf-8');\n    }\n  }\n}\n"
  },
  "src/index.ts": {
    "path": "src/index.ts",
    "content": "export { FileCollector, Options } from './fileCollector';\n"
  },
  "tsconfig.json": {
    "path": "tsconfig.json",
    "content": "{\n  \"compilerOptions\": {\n    \"target\": \"ES2020\",\n    \"module\": \"CommonJS\",\n    \"outDir\": \"./dist\",\n    \"strict\": true,\n    \"esModuleInterop\": true,\n    \"resolveJsonModule\": true,\n    \"skipLibCheck\": true,\n    \"types\": [\"node\"]\n  },\n  \"include\": [\"src/**/*\"]\n}\n"
  },
  "yarn.lock": {
    "path": "yarn.lock",
    "content": "# THIS IS AN AUTOGENERATED FILE. DO NOT EDIT THIS FILE DIRECTLY.\n# yarn lockfile v1\n\n\n\"@types/node@^22.10.10\":\n  version \"22.10.10\"\n  resolved \"https://registry.npmjs.org/@types/node/-/node-22.10.10.tgz\"\n  integrity sha512-X47y/mPNzxviAGY5TcYPtYL8JsY3kAq2n8fMmKoRCxq/c4v4pyGNCzM2R6+M5/umG4ZfHuT+sgqDYqWc9rJ6ww==\n  dependencies:\n    undici-types \"~6.20.0\"\n\n\"@types/yargs-parser@*\":\n  version \"21.0.3\"\n  resolved \"https://registry.npmjs.org/@types/yargs-parser/-/yargs-parser-21.0.3.tgz\"\n  integrity sha512-I4q9QU9MQv4oEOz4tAHJtNz1cwuLxn2F3xcc2iV5WdqLPpUnj30aUuxt1mAxYTG+oe8CZMV/+6rU4S4gRDzqtQ==\n\n\"@types/yargs@^17.0.33\":\n  version \"17.0.33\"\n  resolved \"https://registry.npmjs.org/@types/yargs/-/yargs-17.0.33.tgz\"\n  integrity sha512-WpxBCKWPLr4xSsHgz511rFJAM+wS28w2zEO1QDNY5zM/S8ok70NNfztH0xwhqKyaK0OHCbN98LDAZuy1ctxDkA==\n  dependencies:\n    \"@types/yargs-parser\" \"*\"\n\nansi-regex@^5.0.1:\n  version \"5.0.1\"\n  resolved \"https://registry.npmjs.org/ansi-regex/-/ansi-regex-5.0.1.tgz\"\n  integrity sha512-quJQXlTSUGL2LH9SUXo8VwsY4soanhgo6LNSm84E1LBcE8s3O0wpdiRzyR9z/ZZJMlMWv37qOOb9pdJlMUEKFQ==\n\nansi-styles@^4.0.0:\n  version \"4.3.0\"\n  resolved \"https://registry.npmjs.org/ansi-styles/-/ansi-styles-4.3.0.tgz\"\n  integrity sha512-zbB9rCJAT1rbjiVDb2hqKFHNYLxgtk8NURxZ3IZwD3F6NtxbXZQCnnSi1Lkx+IDohdPlFp222wVALIheZJQSEg==\n  dependencies:\n    color-convert \"^2.0.1\"\n\ncliui@^8.0.1:\n  version \"8.0.1\"\n  resolved \"https://registry.npmjs.org/cliui/-/cliui-8.0.1.tgz\"\n  integrity sha512-BSeNnyus75C4//NQ9gQt1/csTXyo/8Sb+afLAkzAptFuMsod9HFokGNudZpi/oQV73hnVK+sR+5PVRMd+Dr7YQ==\n  dependencies:\n    string-width \"^4.2.0\"\n    strip-ansi \"^6.0.1\"\n    wrap-ansi \"^7.0.0\"\n\ncolor-convert@^2.0.1:\n  version \"2.0.1\"\n  resolved \"https://registry.npmjs.org/color-convert/-/color-convert-2.0.1.tgz\"\n  integrity sha512-RRECPsj7iu/xb5oKYcsFHSppFNnsj/52OVTRKb4zP5onXwVF3zVmmToNcOfGC+CRDpfK/U584fMg38ZHCaElKQ==\n  dependencies:\n    color-name \"~1.1.4\"\n\ncolor-name@~1.1.4:\n  version \"1.1.4\"\n  resolved \"https://registry.npmjs.org/color-name/-/color-name-1.1.4.tgz\"\n  integrity sha512-dOy+3AuW3a2wNbZHIuMZpTcgjGuLU/uBL/ubcZF9OXbDo8ff4O8yVp5Bf0efS8uEoYo5q4Fx7dY9OgQGXgAsQA==\n\nemoji-regex@^8.0.0:\n  version \"8.0.0\"\n  resolved \"https://registry.npmjs.org/emoji-regex/-/emoji-regex-8.0.0.tgz\"\n  integrity sha512-MSjYzcWNOA0ewAHpz0MxpYFvwg6yjy1NG3xteoqz644VCo/RPgnr1/GGt+ic3iJTzQ8Eu3TdM14SawnVUmGE6A==\n\nescalade@^3.1.1:\n  version \"3.2.0\"\n  resolved \"https://registry.npmjs.org/escalade/-/escalade-3.2.0.tgz\"\n  integrity sha512-WUj2qlxaQtO4g6Pq5c29GTcWGDyd8itL8zTlipgECz3JesAiiOKotd8JU6otB3PACgG6xkJUyVhboMS+bje/jA==\n\nget-caller-file@^2.0.5:\n  version \"2.0.5\"\n  resolved \"https://registry.npmjs.org/get-caller-file/-/get-caller-file-2.0.5.tgz\"\n  integrity sha512-DyFP3BM/3YHTQOCUL/w0OZHR0lpKeGrxotcHWcqNEdnltqFwXVfhEBQ94eIo34AfQpo0rGki4cyIiftY06h2Fg==\n\nis-fullwidth-code-point@^3.0.0:\n  version \"3.0.0\"\n  resolved \"https://registry.npmjs.org/is-fullwidth-code-point/-/is-fullwidth-code-point-3.0.0.tgz\"\n  integrity sha512-zymm5+u+sCsSWyD9qNaejV3DFvhCKclKdizYaJUuHA83RLjb7nSuGnddCHGv0hk+KY7BMAlsWeK4Ueg6EV6XQg==\n\nrequire-directory@^2.1.1:\n  version \"2.1.1\"\n  resolved \"https://registry.npmjs.org/require-directory/-/require-directory-2.1.1.tgz\"\n  integrity sha512-fGxEI7+wsG9xrvdjsrlmL22OMTTiHRwAMroiEeMgq8gzoLC/PQr7RsRDSTLUg/bZAZtF+TVIkHc6/4RIKrui+Q==\n\nstring-width@^4.1.0, string-width@^4.2.0, string-width@^4.2.3:\n  version \"4.2.3\"\n  resolved \"https://registry.npmjs.org/string-width/-/string-width-4.2.3.tgz\"\n  integrity sha512-wKyQRQpjJ0sIp62ErSZdGsjMJWsap5oRNihHhu6G7JVO/9jIB6UyevL+tXuOqrng8j/cxKTWyWUwvSTriiZz/g==\n  dependencies:\n    emoji-regex \"^8.0.0\"\n    is-fullwidth-code-point \"^3.0.0\"\n    strip-ansi \"^6.0.1\"\n\nstrip-ansi@^6.0.0, strip-ansi@^6.0.1:\n  version \"6.0.1\"\n  resolved \"https://registry.npmjs.org/strip-ansi/-/strip-ansi-6.0.1.tgz\"\n  integrity sha512-Y38VPSHcqkFrCpFnQ9vuSXmquuv5oXOKpGeT6aGrr3o3Gc9AlVa6JBfUSOCnbxGGZF+/0ooI7KrPuUSztUdU5A==\n  dependencies:\n    ansi-regex \"^5.0.1\"\n\ntypescript@^5.2.0:\n  version \"5.7.3\"\n  resolved \"https://registry.npmjs.org/typescript/-/typescript-5.7.3.tgz\"\n  integrity sha512-84MVSjMEHP+FQRPy3pX9sTVV/INIex71s9TL2Gm5FG/WG1SqXeKyZ0k7/blY/4FdOzI12CBy1vGc4og/eus0fw==\n\nundici-types@~6.20.0:\n  version \"6.20.0\"\n  resolved \"https://registry.npmjs.org/undici-types/-/undici-types-6.20.0.tgz\"\n  integrity sha512-Ny6QZ2Nju20vw1SRHe3d9jVu6gJ+4e3+MMpqu7pqE5HT6WsTSlce++GQmK5UXS8mzV8DSYHrQH+Xrf2jVcuKNg==\n\nwrap-ansi@^7.0.0:\n  version \"7.0.0\"\n  resolved \"https://registry.npmjs.org/wrap-ansi/-/wrap-ansi-7.0.0.tgz\"\n  integrity sha512-YVGIj2kamLSTxw6NsZjoBxfSwsn0ycdesmc4p+Q21c5zPuZ1pl+NfxVdxPtdHvmNVOQ6XSYG4AUtyt/Fi7D16Q==\n  dependencies:\n    ansi-styles \"^4.0.0\"\n    string-width \"^4.1.0\"\n    strip-ansi \"^6.0.0\"\n\ny18n@^5.0.5:\n  version \"5.0.8\"\n  resolved \"https://registry.npmjs.org/y18n/-/y18n-5.0.8.tgz\"\n  integrity sha512-0pfFzegeDWJHJIAmTLRP2DwHjdF5s7jo9tuztdQxAhINCdvS+3nGINqPd00AphqJR/0LhANUS6/+7SCb98YOfA==\n\nyargs-parser@^21.1.1:\n  version \"21.1.1\"\n  resolved \"https://registry.npmjs.org/yargs-parser/-/yargs-parser-21.1.1.tgz\"\n  integrity sha512-tVpsJW7DdjecAiFpbIB1e3qxIQsE6NoPc5/eTdrbbIC4h0LVsWhnoa3g+m2HclBIujHzsxZ4VJVA+GUuc2/LBw==\n\nyargs@^17.7.2:\n  version \"17.7.2\"\n  resolved \"https://registry.npmjs.org/yargs/-/yargs-17.7.2.tgz\"\n  integrity sha512-7dSzzRQ++CKnNI/krKnYRV7JKKPUXMEh61soaHKg9mrWEhzFWhFnxPxGl+69cD1Ou63C13NUPCnmIcrvqCuM6w==\n  dependencies:\n    cliui \"^8.0.1\"\n    escalade \"^3.1.1\"\n    get-caller-file \"^2.0.5\"\n    require-directory \"^2.1.1\"\n    string-width \"^4.2.3\"\n    y18n \"^5.0.5\"\n    yargs-parser \"^21.1.1\"\n"
  }
}